multiurl.py
django_multiurl-1.5.0.dist-info/LICENSE.txt
django_multiurl-1.5.0.dist-info/METADATA
django_multiurl-1.5.0.dist-info/WHEEL
django_multiurl-1.5.0.dist-info/top_level.txt
django_multiurl-1.5.0.dist-info/RECORD
