Metadata-Version: 2.1
Name: django-multiurl
Version: 1.5.0
Summary: Allow multiple views to match the same URL.
Home-page: https://github.com/raiderrobert/django-multiurl
Author: Jacob Kaplan-Moss and Robert Roskam
Author-email: raiderrobert@gmail.com
License: BSD
Download-URL: https://github.com/raiderrobert/django-multiurl/tarball/v1.5.0
Keywords: django urls
Platform: UNKNOWN
Classifier: Development Status :: 4 - Beta
Classifier: Environment :: Web Environment
Classifier: Framework :: Django
Classifier: Intended Audience :: Developers
Classifier: License :: OSI Approved :: BSD License
Classifier: Natural Language :: English
Classifier: Programming Language :: Python
Classifier: Programming Language :: Python :: 2.7
Classifier: Programming Language :: Python :: 3.4
Classifier: Programming Language :: Python :: 3.5
Classifier: Programming Language :: Python :: 3.6
License-File: LICENSE.txt
Requires-Dist: django (>=1.11)
